Workbook

Sheet Resumo
A1: Ação de arrecadação solidária Efeito Rebote: resumo
A2: Bilhetes no total | B2: 2400
A3: Bilhetes vendidos (com comprador) | B3: =COUNTIF(Vendas!D2:D2401,"<>")
A4: Bilhetes pagos | B4: =COUNTIF(Vendas!G2:G2401,"Sim")
A5: Arrecadado (R$) | B5: =B4*5
A6: % vendido (pago) | B6: =B4/B2
A7: Custo estimado do prêmio (R$) | B7: 1600
A8: Ponto de equilíbrio (bilhetes) | B8: =B7/5
A9: Compra do prêmio liberada? (≥ 2× equilíbrio) | B9: =IF(B4>=2*B8,"SIM","Ainda não")
A10: Saldo para itens após o prêmio (R$) | B10: =B5-B7
A11: PIX recebidos (R$) | B11: =COUNTIFS(Vendas!F2:F2401,"PIX",Vendas!G2:G2401,"Sim")*5
A12: Dinheiro recebido (R$) | B12: =COUNTIFS(Vendas!F2:F2401,"Dinheiro",Vendas!G2:G2401,"Sim")*5
A13: Prazo final de vendas | B13: 30/10/2026 23h59
A14: Sorteio | B14: 02/11/2026, ao vivo @efeitorebote.oficial

Sheet Distribuição
A1: Aluno nº | B1: Nome | C1: Período | D1: Bilhete inicial | E1: Bilhete final | F1: Assinatura de recebimento
A2: 1 | D2: 0001 | E2: 0030
A3: 2 | D3: 0031 | E3: 0060
A4: 3 | D4: 0061 | E4: 0090
A5: 4 | D5: 0091 | E5: 0120
A6: 5 | D6: 0121 | E6: 0150
A7: 6 | D7: 0151 | E7: 0180
A8: 7 | D8: 0181 | E8: 0210
A9: 8 | D9: 0211 | E9: 0240
A10: 9 | D10: 0241 | E10: 0270
A11: 10 | D11: 0271 | E11: 0300
A12: 11 | D12: 0301 | E12: 0330
A13: 12 | D13: 0331 | E13: 0360
... A81: 80 | D81: 2371 | E81: 2400

Sheet Vendas
A1: Bilhete | B1: Aluno nº | C1: Vendedor(a) | D1: Comprador | E1: Telefone | F1: Pagamento | G1: Pago? | H1: Data | I1: Conferido (comissão)
A2: 0001 | B2: 1 | C2: =IF(VLOOKUP(B2,'Distribuição'!A:B,2,FALSE)="","",VLOOKUP(B2,'Distribuição'!A:B,2,FALSE))
A3: 0002 | B3: 1 | C3: =IF(VLOOKUP(B3,'Distribuição'!A:B,2,FALSE)="","",VLOOKUP(B3,'Distribuição'!A:B,2,FALSE))
A4: 0003 | B4: 1 | C4: =IF(VLOOKUP(B4,'Distribuição'!A:B,2,FALSE)="","",VLOOKUP(B4,'Distribuição'!A:B,2,FALSE))
A5: 0004 | B5: 1 | C5: =IF(VLOOKUP(B5,'Distribuição'!A:B,2,FALSE)="","",VLOOKUP(B5,'Distribuição'!A:B,2,FALSE))
A6: 0005 | B6: 1 | C6: =IF(VLOOKUP(B6,'Distribuição'!A:B,2,FALSE)="","",VLOOKUP(B6,'Distribuição'!A:B,2,FALSE))
A7: 0006 | B7: 1 | C7: =IF(VLOOKUP(B7,'Distribuição'!A:B,2,FALSE)="","",VLOOKUP(B7,'Distribuição'!A:B,2,FALSE))
A8: 0007 | B8: 1 | C8: =IF(VLOOKUP(B8,'Distribuição'!A:B,2,FALSE)="","",VLOOKUP(B8,'Distribuição'!A:B,2,FALSE))
A9: 0008 | B9: 1 | C9: =IF(VLOOKUP(B9,'Distribuição'!A:B,2,FALSE)="","",VLOOKUP(B9,'Distribuição'!A:B,2,FALSE))
A10: 0009 | B10: 1 | C10: =IF(VLOOKUP(B10,'Distribuição'!A:B,2,FALSE)="","",VLOOKUP(B10,'Distribuição'!A:B,2,FALSE))
A11: 0010 | B11: 1 | C11: =IF(VLOOKUP(B11,'Distribuição'!A:B,2,FALSE)="","",VLOOKUP(B11,'Distribuição'!A:B,2,FALSE))
A12: 0011 | B12: 1 | C12: =IF(VLOOKUP(B12,'Distribuição'!A:B,2,FALSE)="","",VLOOKUP(B12,'Distribuição'!A:B,2,FALSE))
A13: 0012 | B13: 1 | C13: =IF(VLOOKUP(B13,'Distribuição'!A:B,2,FALSE)="","",VLOOKUP(B13,'Distribuição'!A:B,2,FALSE))
... A2401: 2400 | B2401: 80 | C2401: =IF(VLOOKUP(B2401,'Distribuição'!A:B,2,FALSE)="","",VLOOKUP(B2401,'Distribuição'!A:B,2,FALSE))

Sheet Por aluno
A1: Aluno nº | B1: Nome | C1: Vendidos | D1: Pagos | E1: Valor pago (R$) | F1: Restantes
A2: 1 | B2: =IF('Distribuição'!B2="","",'Distribuição'!B2) | C2: =COUNTIFS(Vendas!B:B,A2,Vendas!D:D,"<>") | D2: =COUNTIFS(Vendas!B:B,A2,Vendas!G:G,"Sim") | E2: =D2*5 | F2: =30-C2
A3: 2 | B3: =IF('Distribuição'!B3="","",'Distribuição'!B3) | C3: =COUNTIFS(Vendas!B:B,A3,Vendas!D:D,"<>") | D3: =COUNTIFS(Vendas!B:B,A3,Vendas!G:G,"Sim") | E3: =D3*5 | F3: =30-C3
A4: 3 | B4: =IF('Distribuição'!B4="","",'Distribuição'!B4) | C4: =COUNTIFS(Vendas!B:B,A4,Vendas!D:D,"<>") | D4: =COUNTIFS(Vendas!B:B,A4,Vendas!G:G,"Sim") | E4: =D4*5 | F4: =30-C4
A5: 4 | B5: =IF('Distribuição'!B5="","",'Distribuição'!B5) | C5: =COUNTIFS(Vendas!B:B,A5,Vendas!D:D,"<>") | D5: =COUNTIFS(Vendas!B:B,A5,Vendas!G:G,"Sim") | E5: =D5*5 | F5: =30-C5
A6: 5 | B6: =IF('Distribuição'!B6="","",'Distribuição'!B6) | C6: =COUNTIFS(Vendas!B:B,A6,Vendas!D:D,"<>") | D6: =COUNTIFS(Vendas!B:B,A6,Vendas!G:G,"Sim") | E6: =D6*5 | F6: =30-C6
A7: 6 | B7: =IF('Distribuição'!B7="","",'Distribuição'!B7) | C7: =COUNTIFS(Vendas!B:B,A7,Vendas!D:D,"<>") | D7: =COUNTIFS(Vendas!B:B,A7,Vendas!G:G,"Sim") | E7: =D7*5 | F7: =30-C7
A8: 7 | B8: =IF('Distribuição'!B8="","",'Distribuição'!B8) | C8: =COUNTIFS(Vendas!B:B,A8,Vendas!D:D,"<>") | D8: =COUNTIFS(Vendas!B:B,A8,Vendas!G:G,"Sim") | E8: =D8*5 | F8: =30-C8
A9: 8 | B9: =IF('Distribuição'!B9="","",'Distribuição'!B9) | C9: =COUNTIFS(Vendas!B:B,A9,Vendas!D:D,"<>") | D9: =COUNTIFS(Vendas!B:B,A9,Vendas!G:G,"Sim") | E9: =D9*5 | F9: =30-C9
A10: 9 | B10: =IF('Distribuição'!B10="","",'Distribuição'!B10) | C10: =COUNTIFS(Vendas!B:B,A10,Vendas!D:D,"<>") | D10: =COUNTIFS(Vendas!B:B,A10,Vendas!G:G,"Sim") | E10: =D10*5 | F10: =30-C10
A11: 10 | B11: =IF('Distribuição'!B11="","",'Distribuição'!B11) | C11: =COUNTIFS(Vendas!B:B,A11,Vendas!D:D,"<>") | D11: =COUNTIFS(Vendas!B:B,A11,Vendas!G:G,"Sim") | E11: =D11*5 | F11: =30-C11
A12: 11 | B12: =IF('Distribuição'!B12="","",'Distribuição'!B12) | C12: =COUNTIFS(Vendas!B:B,A12,Vendas!D:D,"<>") | D12: =COUNTIFS(Vendas!B:B,A12,Vendas!G:G,"Sim") | E12: =D12*5 | F12: =30-C12
A13: 12 | B13: =IF('Distribuição'!B13="","",'Distribuição'!B13) | C13: =COUNTIFS(Vendas!B:B,A13,Vendas!D:D,"<>") | D13: =COUNTIFS(Vendas!B:B,A13,Vendas!G:G,"Sim") | E13: =D13*5 | F13: =30-C13
... A81: 80 | B81: =IF('Distribuição'!B81="","",'Distribuição'!B81) | C81: =COUNTIFS(Vendas!B:B,A81,Vendas!D:D,"<>") | D81: =COUNTIFS(Vendas!B:B,A81,Vendas!G:G,"Sim") | E81: =D81*5 | F81: =30-C81
